duplidele/__init__.py
duplidele/duplidele.py
duplidele-2.3.0.dist-info/METADATA
duplidele-2.3.0.dist-info/WHEEL
duplidele-2.3.0.dist-info/top_level.txt
duplidele-2.3.0.dist-info/RECORD
